pyhmer/__init__.py
pyhmer/animal_rhymes.csv
pyhmer-0.0.8.dist-info/LICENSE
pyhmer-0.0.8.dist-info/METADATA
pyhmer-0.0.8.dist-info/WHEEL
pyhmer-0.0.8.dist-info/top_level.txt
pyhmer-0.0.8.dist-info/RECORD
