Metadata-Version: 2.1
Name: pyhmer
Version: 0.0.8
Summary: create rhyming noun + adjective pairs
Home-page: https://github.com/lukas-schillinger/pyhmer
Author: Lukas-Schillinger
Author-email: lukas@schillingertools.com
Project-URL: Bug Tracker, https://github.com/lukas-schillinger/pyhmer/issues
Classifier: Programming Language :: Python :: 3
Classifier: License :: OSI Approved :: MIT License
Classifier: Operating System :: OS Independent
License-File: LICENSE
